docs_server/__init__.py
docs_server/dev_mcp_server.py
docs_server/doc_store.py
docs_server/exceptions.py
docs_server/search.py
docs_server/server.py
docs/markdown/apis/action.md
docs/markdown/apis/apis.md
docs/markdown/apis/assets.md
docs/markdown/apis/broadcast.md
docs/markdown/apis/context-menu.md
docs/markdown/apis/fog.md
docs/markdown/apis/grid.md
docs/markdown/apis/history.md
docs/markdown/apis/interaction.md
docs/markdown/apis/items.md
docs/markdown/apis/local.md
docs/markdown/apis/modal.md
docs/markdown/apis/notification.md
docs/markdown/apis/party.md
docs/markdown/apis/player.md
docs/markdown/apis/popover.md
docs/markdown/apis/room.md
docs/markdown/apis/scene.md
docs/markdown/apis/theme.md
docs/markdown/apis/tool.md
docs/markdown/apis/viewport.md
docs/markdown/reference/billboard.md
docs/markdown/reference/bounding-box.md
docs/markdown/reference/builders.md
docs/markdown/reference/curve.md
docs/markdown/reference/dynamic-fog.md
docs/markdown/reference/effect.md
docs/markdown/reference/effects.md
docs/markdown/reference/filters.md
docs/markdown/reference/image-upload.md
docs/markdown/reference/image.md
docs/markdown/reference/item.md
docs/markdown/reference/items.md
docs/markdown/reference/label.md
docs/markdown/reference/light.md
docs/markdown/reference/line.md
docs/markdown/reference/manifest.md
docs/markdown/reference/math-2.md
docs/markdown/reference/math-m.md
docs/markdown/reference/math.md
docs/markdown/reference/matrix.md
docs/markdown/reference/metadata.md
docs/markdown/reference/path.md
docs/markdown/reference/permission.md
docs/markdown/reference/player.md
docs/markdown/reference/pointer.md
docs/markdown/reference/reference.md
docs/markdown/reference/ruler.md
docs/markdown/reference/scene-upload.md
docs/markdown/reference/shape.md
docs/markdown/reference/text-content.md
docs/markdown/reference/text.md
docs/markdown/reference/vector2.md
docs/markdown/reference/vector3.md
docs/markdown/reference/wall.md
mcp_for_owlbear_rodeo-0.1.0.dist-info/METADATA
mcp_for_owlbear_rodeo-0.1.0.dist-info/WHEEL
mcp_for_owlbear_rodeo-0.1.0.dist-info/entry_points.txt
mcp_for_owlbear_rodeo-0.1.0.dist-info/RECORD
