Metadata-Version: 2.4
Name: mcp-for-owlbear-rodeo
Version: 0.1.0
Summary: Owlbear Rodeo 文档的 MCP 服务端, 支持搜索与资源读取
Author: DnD5e Tools
Keywords: documentation,mcp,owlbear
Requires-Python: >=3.13
Requires-Dist: mcp[cli]>=1.21.0
